nonebot_plugin_picsbank/__init__.py
nonebot_plugin_picsbank/data_source.py
nonebot_plugin_picsbank/utils.py
nonebot_plugin_picsbank-0.2.0.dist-info/LICENSE
nonebot_plugin_picsbank-0.2.0.dist-info/WHEEL
nonebot_plugin_picsbank-0.2.0.dist-info/METADATA
nonebot_plugin_picsbank-0.2.0.dist-info/RECORD
