Metadata-Version: 2.1
Name: nonebot-plugin-picsbank
Version: 0.2.0
Summary: 
Home-page: https://github.com/Diaosi1111/nonebot_plugin_picsbank
License: MIT
Keywords: nonebot,nonebot2,picsbank
Author: Alex Newton
Author-email: sharenfan222@gmail.com
Requires-Python: >=3.8,<3.11
Classifier: License :: OSI Approved :: MIT License
Classifier: Programming Language :: Python :: 3
Classifier: Programming Language :: Python :: 3.10
Classifier: Programming Language :: Python :: 3.8
Classifier: Programming Language :: Python :: 3.9
Requires-Dist: Pillow (>=8.2.0,<9.0.0)
Requires-Dist: aiohttp (>=3.7.4.post0,<4.0.0)
Requires-Dist: nonebot-adapter-onebot
Requires-Dist: nonebot2 (>=2.0.0-beta.1,<3.0.0)
Requires-Dist: numpy (>=1.21.4,<2.0.0)
Requires-Dist: opencv-python (>=4.5.4,<5.0.0)
Requires-Dist: ujson (>=4.0.2,<5.0.0)
Project-URL: Repository, https://github.com/Diaosi1111/nonebot_plugin_picsbank
